{
  "id": "nc-20260218-917804",
  "first_name": "suresh",
  "last_name": "girimaji",
  "full_name": "suresh girimaji",
  "company": "NalpakGroup.com",
  "position": "Partner",
  "linkedin_url": "https://www.linkedin.com/in/suresh-girimaji-44314547",
  "relationship_type": "colleague",
  "relationship_strength": "moderate",
  "business_value": "unknown",
  "tags": [],
  "last_contacted": "26 Aug 2014",
  "imported_from": "linkedin",
  "created_at": "2026-02-18T22:15:17.804Z",
  "updated_at": "2026-02-18T22:15:17.804Z"
}