{
  "id": "nc-20260218-917435",
  "first_name": "Melanie",
  "last_name": "Rieback",
  "full_name": "Melanie Rieback",
  "company": "Non-Extractive Capital",
  "position": "Co-founder/CEO",
  "linkedin_url": "https://www.linkedin.com/in/mrieback",
  "relationship_type": "colleague",
  "relationship_strength": "moderate",
  "business_value": "unknown",
  "tags": [],
  "last_contacted": "16 May 2024",
  "imported_from": "linkedin",
  "created_at": "2026-02-18T22:15:17.435Z",
  "updated_at": "2026-02-18T22:15:17.435Z"
}